graviteeio_cli/__init__.py
graviteeio_cli/__main__.py
graviteeio_cli/__version__.py
graviteeio_cli/cli.py
graviteeio_cli/environments.py
graviteeio_cli/exeptions.py
graviteeio_cli/commands/__init__.py
graviteeio_cli/commands/linter.py
graviteeio_cli/commands/profiles.py
graviteeio_cli/commands/am/__init__.py
graviteeio_cli/commands/am/am.py
graviteeio_cli/commands/am/auth/__init__.py
graviteeio_cli/commands/am/auth/auth.py
graviteeio_cli/commands/apim/__init__.py
graviteeio_cli/commands/apim/apim.py
graviteeio_cli/commands/apim/apis/__init__.py
graviteeio_cli/commands/apim/apis/apis.py
graviteeio_cli/commands/apim/apis/definition.py
graviteeio_cli/commands/apim/apis/deploy.py
graviteeio_cli/commands/apim/apis/get.py
graviteeio_cli/commands/apim/apis/health.py
graviteeio_cli/commands/apim/apis/logs.py
graviteeio_cli/commands/apim/apis/ls.py
graviteeio_cli/commands/apim/apis/spec.py
graviteeio_cli/commands/apim/apis/start.py
graviteeio_cli/commands/apim/apis/status.py
graviteeio_cli/commands/apim/apis/stop.py
graviteeio_cli/commands/apim/apis/utils.py
graviteeio_cli/commands/apim/apis/definition_group/__init__.py
graviteeio_cli/commands/apim/apis/definition_group/apply.py
graviteeio_cli/commands/apim/apis/definition_group/create.py
graviteeio_cli/commands/apim/apis/definition_group/diff.py
graviteeio_cli/commands/apim/apis/definition_group/generate.py
graviteeio_cli/commands/apim/apis/definition_group/lint.py
graviteeio_cli/commands/apim/apis/plugins/__init__.py
graviteeio_cli/commands/apim/apis/plugins/cmd_test.py
graviteeio_cli/commands/apim/apis/spec_group/__init__.py
graviteeio_cli/commands/apim/apis/spec_group/apply.py
graviteeio_cli/commands/apim/apis/spec_group/lint.py
graviteeio_cli/commands/apim/apps/__init__.py
graviteeio_cli/commands/apim/apps/apply.py
graviteeio_cli/commands/apim/apps/apps.py
graviteeio_cli/commands/apim/apps/create.py
graviteeio_cli/commands/apim/apps/generate.py
graviteeio_cli/commands/apim/apps/ls.py
graviteeio_cli-0.4.dist-info/LICENSE.txt
graviteeio_cli-0.4.dist-info/METADATA
graviteeio_cli-0.4.dist-info/WHEEL
graviteeio_cli-0.4.dist-info/entry_points.txt
graviteeio_cli-0.4.dist-info/top_level.txt
graviteeio_cli-0.4.dist-info/RECORD
