Metadata-Version: 2.1
Name: graviteeio-cli
Version: 0.4
Summary: Command line Client program in Python for graviteeio platform
Home-page: https://github.com/gravitee-io/graviteeio-cli
Author: Guillaume Gillon
Author-email: guillaume.gillon@outlook.com
License: Apache License Version 2.0
Keywords: Graviteeio,gio,gravitee,configuration,cli
Platform: UNKNOWN
Classifier: Intended Audience :: Developers
Classifier: Topic :: Utilities
Classifier: License :: OSI Approved :: Apache Software License
Classifier: Natural Language :: English
Classifier: Operating System :: OS Independent
Classifier: Programming Language :: Python :: 3.7
Classifier: Programming Language :: Python :: 3.8
Classifier: Programming Language :: Python :: 3.9
Requires-Dist: click (<8.0,>=7.0)
Requires-Dist: configparser (==3.8.1)
Requires-Dist: requests (>=2.22.0)
Requires-Dist: click-completion (>=0.5.2)
Requires-Dist: terminaltables (>=3.1.0)
Requires-Dist: pyyaml (>=5.1.2)
Requires-Dist: jinja2 (>=2.10.1)
Requires-Dist: dictdiffer (>=0.8.0)
Requires-Dist: jmespath (>=0.10.0)
Requires-Dist: asyncio (==3.4.3)
Requires-Dist: pytimeparse (==1.1.8)
Requires-Dist: termgraph (==0.2.1)
Requires-Dist: jsonschema (==3.2.0)
Requires-Dist: jsonpath-ng (==1.5.2)
Provides-Extra: test
Requires-Dist: coverage ; extra == 'test'
Requires-Dist: pytest ; extra == 'test'
Requires-Dist: pytest-cov ; extra == 'test'
